setup.py
ajax_validation/__init__.py
ajax_validation/models.py
ajax_validation/urls.py
ajax_validation/utils.py
ajax_validation/views.py
ajax_validation/templatetags/__init__.py
ajax_validation/templatetags/jquery_validation.py
django_ajax_validation.egg-info/PKG-INFO
django_ajax_validation.egg-info/SOURCES.txt
django_ajax_validation.egg-info/dependency_links.txt
django_ajax_validation.egg-info/top_level.txt