Metadata-Version: 1.0
Name: django-ajax-validation
Version: 0.1.1
Summary: Provides support for doing validation using Ajax(currently with jQuery) using your existing Django forms.
Home-page: http://github.com/alex/django-ajax-validation/tree/master
Author: Alex Gaynor
Author-email: alex.gaynor@gmail.com
License: UNKNOWN
Platform: UNKNOWN
Classifier: Development Status :: 3 - Alpha
Classifier: Environment :: Web Environment
Classifier: Intended Audience :: Developers
Classifier: License :: OSI Approved :: BSD License
Classifier: Operating System :: OS Independent
Classifier: Programming Language :: Python
Classifier: Framework :: Django
